xhsmcpqhzy/__init__.py
xhsmcpqhzy/__main__.py
xhsmcpqhzy/py.typed
xhsmcpqhzy/xhsmcpqhzy.py
xhsmcpqhzy-0.1.6.dist-info/METADATA
xhsmcpqhzy-0.1.6.dist-info/WHEEL
xhsmcpqhzy-0.1.6.dist-info/entry_points.txt
xhsmcpqhzy-0.1.6.dist-info/RECORD
