Metadata-Version: 2.4
Name: xhsmcpqhzy
Version: 0.1.6
Summary: Add your description here
Author-email: warriorsChampion <11158048+warriorschampion@user.noreply.gitee.com>
Requires-Python: >=3.10
Requires-Dist: build>=1.2.2.post1
Requires-Dist: mcp[cli]>=1.10.0
Requires-Dist: modelscope>=1.27.1
Requires-Dist: numpy>=2.2.6
Requires-Dist: opencv-python>=4.11.0.86
Requires-Dist: pillow>=11.2.1
Requires-Dist: torch>=2.7.1
Requires-Dist: transformers>=4.53.0
Requires-Dist: twine>=6.1.0
